{
  "pair": "Chinese + Thai",
  "bridges": [
    {
      "name": "fish sauce",
      "score": 418.07033828527193,
      "connects_a": [
        "hoisin sauce",
        "ginger",
        "pork"
      ],
      "connects_b": [
        "cilantro leaves",
        "bean sprouts",
        "shrimp"
      ]
    },
    {
      "name": "bean sprouts",
      "score": 340.7215136929801,
      "connects_a": [
        "hoisin sauce",
        "ginger",
        "mushrooms"
      ],
      "connects_b": [
        "cilantro leaves",
        "fish sauce",
        "shrimp"
      ]
    },
    {
      "name": "sriracha",
      "score": 288.34081094143096,
      "connects_a": [
        "hoisin sauce",
        "ginger",
        "soy sauce"
      ],
      "connects_b": [
        "cilantro leaves",
        "lime",
        "ginger"
      ]
    },
    {
      "name": "hoisin sauce",
      "score": 286.2186615057622,
      "connects_a": [
        "cabbage",
        "corn starch",
        "sodium soy sauce"
      ],
      "connects_b": [
        "ginger",
        "soy sauce",
        "chicken breasts"
      ]
    },
    {
      "name": "ginger",
      "score": 274.95631922766876,
      "connects_a": [
        "hoisin sauce",
        "pork",
        "soy sauce"
      ],
      "connects_b": [
        "coconut milk",
        "soy sauce",
        "chiles"
      ]
    },
    {
      "name": "rice vinegar",
      "score": 266.60980740787176,
      "connects_a": [
        "cabbage",
        "corn starch",
        "sodium soy sauce"
      ],
      "connects_b": [
        "ginger",
        "chiles",
        "chicken breasts"
      ]
    },
    {
      "name": "oyster sauce",
      "score": 264.1697307224334,
      "connects_a": [
        "cabbage",
        "corn starch",
        "sodium soy sauce"
      ],
      "connects_b": [
        "ginger",
        "soy sauce",
        "chicken breasts"
      ]
    },
    {
      "name": "cabbage",
      "score": 240.93355355148552,
      "connects_a": [
        "hoisin sauce",
        "ginger",
        "pork"
      ],
      "connects_b": [
        "cilantro leaves",
        "lime",
        "ginger"
      ]
    },
    {
      "name": "scallions",
      "score": 240.883536881153,
      "connects_a": [
        "hoisin sauce",
        "ginger",
        "pork"
      ],
      "connects_b": [
        "cilantro leaves",
        "lime",
        "ginger"
      ]
    },
    {
      "name": "sodium soy sauce",
      "score": 216.18233946853167,
      "connects_a": [
        "hoisin sauce",
        "pork",
        "ginger"
      ],
      "connects_b": [
        "coconut milk",
        "ginger",
        "chicken breasts"
      ]
    }
  ],
  "novel_from_a": [
    {
      "name": "baby arugula",
      "pairs_with": "olive oil",
      "strength": 1
    },
    {
      "name": "radicchio",
      "pairs_with": "olive oil",
      "strength": 1
    },
    {
      "name": "anchovies",
      "pairs_with": "olive oil",
      "strength": 1
    },
    {
      "name": "spun",
      "pairs_with": "olive oil",
      "strength": 1
    },
    {
      "name": "petite",
      "pairs_with": "olive oil",
      "strength": 1
    },
    {
      "name": "squid",
      "pairs_with": "olive oil",
      "strength": 1
    },
    {
      "name": "turkey sausage",
      "pairs_with": "olive oil",
      "strength": 1
    },
    {
      "name": "veal",
      "pairs_with": "cloves",
      "strength": 1
    },
    {
      "name": "anchovies",
      "pairs_with": "cloves",
      "strength": 1
    },
    {
      "name": "petite",
      "pairs_with": "cloves",
      "strength": 1
    }
  ],
  "novel_from_b": [
    {
      "name": "serrano chili",
      "pairs_with": "cloves",
      "strength": 1
    },
    {
      "name": "bunch cilantro",
      "pairs_with": "cloves",
      "strength": 1
    },
    {
      "name": "porcini mushrooms",
      "pairs_with": "cloves",
      "strength": 1
    },
    {
      "name": "parmigiano",
      "pairs_with": "cloves",
      "strength": 1
    },
    {
      "name": "crusty bread",
      "pairs_with": "cloves",
      "strength": 1
    },
    {
      "name": "eggplants",
      "pairs_with": "cloves",
      "strength": 1
    },
    {
      "name": "serrano",
      "pairs_with": "cloves",
      "strength": 1
    },
    {
      "name": "littleneck clams",
      "pairs_with": "cloves",
      "strength": 1
    },
    {
      "name": "1/4 cup chopped fresh",
      "pairs_with": "cloves",
      "strength": 1
    },
    {
      "name": "leg",
      "pairs_with": "cloves",
      "strength": 1
    }
  ]
}