{
  "pair": "Pakistan + Spanish",
  "bridges": [
    {
      "name": "garam masala",
      "score": 190.06839975187782,
      "connects_a": [
        "coriander",
        "basmati rice",
        "tomatoes"
      ],
      "connects_b": [
        "tomatoes",
        "cumin",
        "onion"
      ]
    },
    {
      "name": "tumeric",
      "score": 90.25476534447176,
      "connects_a": [
        "mustard seeds",
        "coriander",
        "garam masala"
      ],
      "connects_b": [
        "tomatoes",
        "cumin",
        "onion"
      ]
    },
    {
      "name": "cumin seeds",
      "score": 84.10364299646703,
      "connects_a": [
        "coriander",
        "garam masala",
        "basmati rice"
      ],
      "connects_b": [
        "paprika",
        "tomatoes",
        "cumin"
      ]
    },
    {
      "name": "bay leaf",
      "score": 81.72896338740817,
      "connects_a": [
        "cinnamon sticks",
        "garam masala",
        "basmati rice"
      ],
      "connects_b": [
        "carrot",
        "tomatoes",
        "chorizo"
      ]
    },
    {
      "name": "coriander",
      "score": 80.20676265769188,
      "connects_a": [
        "garam masala",
        "basmati rice",
        "tomatoes"
      ],
      "connects_b": [
        "paprika",
        "tomatoes",
        "cumin"
      ]
    },
    {
      "name": "coriander powder",
      "score": 80.15621523534114,
      "connects_a": [
        "garam masala",
        "tumeric",
        "tomatoes"
      ],
      "connects_b": [
        "tomatoes",
        "cumin",
        "onion"
      ]
    },
    {
      "name": "turmeric",
      "score": 80.15507929482553,
      "connects_a": [
        "coriander",
        "garam masala",
        "basmati rice"
      ],
      "connects_b": [
        "paprika",
        "tomatoes",
        "cumin"
      ]
    },
    {
      "name": "chiles",
      "score": 78.37226765860659,
      "connects_a": [
        "coconut milk",
        "cinnamon sticks",
        "coriander"
      ],
      "connects_b": [
        "coarsely",
        "taste",
        "cumin"
      ]
    },
    {
      "name": "mustard seeds",
      "score": 76.05919209893314,
      "connects_a": [
        "coriander",
        "garam masala",
        "tomatoes"
      ],
      "connects_b": [
        "peas",
        "tomatoes",
        "cumin"
      ]
    },
    {
      "name": "allspice",
      "score": 66.29405674966588,
      "connects_a": [
        "cinnamon sticks",
        "coriander",
        "mustard seeds"
      ],
      "connects_b": [
        "coarsely",
        "orange",
        "cumin"
      ]
    }
  ],
  "novel_from_a": [
    {
      "name": "petite",
      "pairs_with": "olive oil",
      "strength": 1
    },
    {
      "name": "lamb shanks",
      "pairs_with": "olive oil",
      "strength": 1
    },
    {
      "name": "petite",
      "pairs_with": "cloves",
      "strength": 1
    },
    {
      "name": "lamb shanks",
      "pairs_with": "cloves",
      "strength": 1
    },
    {
      "name": "cardamom pods",
      "pairs_with": "cloves",
      "strength": 1
    },
    {
      "name": "granny smith apples",
      "pairs_with": "butter",
      "strength": 1
    },
    {
      "name": "petite",
      "pairs_with": "onion",
      "strength": 1
    },
    {
      "name": "okra",
      "pairs_with": "onion",
      "strength": 1
    },
    {
      "name": "capsicum",
      "pairs_with": "onion",
      "strength": 1
    },
    {
      "name": "lentil",
      "pairs_with": "onion",
      "strength": 1
    }
  ],
  "novel_from_b": [
    {
      "name": "chorizo",
      "pairs_with": "olive oil",
      "strength": 1
    },
    {
      "name": "for drizzling",
      "pairs_with": "olive oil",
      "strength": 1
    },
    {
      "name": "handful pine nuts",
      "pairs_with": "olive oil",
      "strength": 1
    },
    {
      "name": "bunch kale",
      "pairs_with": "olive oil",
      "strength": 1
    },
    {
      "name": "marzano",
      "pairs_with": "olive oil",
      "strength": 1
    },
    {
      "name": "pass",
      "pairs_with": "olive oil",
      "strength": 1
    },
    {
      "name": "center cut",
      "pairs_with": "olive oil",
      "strength": 1
    },
    {
      "name": "romano",
      "pairs_with": "olive oil",
      "strength": 1
    },
    {
      "name": "heads garlic",
      "pairs_with": "olive oil",
      "strength": 1
    },
    {
      "name": "palm",
      "pairs_with": "olive oil",
      "strength": 1
    }
  ]
}