{
  "pair": "Caribbean + Chinese",
  "bridges": [
    {
      "name": "fish sauce",
      "score": 199.94668352773874,
      "connects_a": [
        "cilantro leaves",
        "pineapple",
        "ginger"
      ],
      "connects_b": [
        "shrimp",
        "hoisin sauce",
        "rice vinegar"
      ]
    },
    {
      "name": "rice vinegar",
      "score": 190.4355767199084,
      "connects_a": [
        "honey",
        "pineapple",
        "ginger"
      ],
      "connects_b": [
        "rice wine",
        "honey",
        "soy sauce"
      ]
    },
    {
      "name": "hoisin sauce",
      "score": 176.1345609266229,
      "connects_a": [
        "honey",
        "ginger",
        "rice"
      ],
      "connects_b": [
        "rice wine",
        "honey",
        "soy sauce"
      ]
    },
    {
      "name": "bean sprouts",
      "score": 170.36075684649006,
      "connects_a": [
        "cilantro leaves",
        "ginger",
        "lime"
      ],
      "connects_b": [
        "shrimp",
        "hoisin sauce",
        "canola oil"
      ]
    },
    {
      "name": "sriracha",
      "score": 162.19170615455494,
      "connects_a": [
        "cilantro leaves",
        "honey",
        "ginger"
      ],
      "connects_b": [
        "honey",
        "hoisin sauce",
        "corn starch"
      ]
    },
    {
      "name": "sodium soy sauce",
      "score": 162.13675460139876,
      "connects_a": [
        "honey",
        "pineapple",
        "ginger"
      ],
      "connects_b": [
        "pepper flakes",
        "honey",
        "hoisin sauce"
      ]
    },
    {
      "name": "ginger",
      "score": 128.3129489729121,
      "connects_a": [
        "pineapple",
        "scallions",
        "garlic"
      ],
      "connects_b": [
        "rice wine",
        "hoisin sauce",
        "corn starch"
      ]
    },
    {
      "name": "snow peas",
      "score": 128.058937965695,
      "connects_a": [
        "bell pepper",
        "ginger",
        "rice"
      ],
      "connects_b": [
        "shrimp",
        "corn starch",
        "rice vinegar"
      ]
    },
    {
      "name": "cabbage",
      "score": 120.46677677574276,
      "connects_a": [
        "cilantro leaves",
        "ginger",
        "lime"
      ],
      "connects_b": [
        "rice wine",
        "hoisin sauce",
        "corn starch"
      ]
    },
    {
      "name": "peanut oil",
      "score": 112.25313081908865,
      "connects_a": [
        "cilantro leaves",
        "ginger",
        "lime"
      ],
      "connects_b": [
        "rice wine",
        "shrimp",
        "hoisin sauce"
      ]
    }
  ],
  "novel_from_a": [
    {
      "name": "basil chiffonade",
      "pairs_with": "cloves",
      "strength": 1
    },
    {
      "name": "chipotle puree",
      "pairs_with": "cloves",
      "strength": 1
    },
    {
      "name": "oregano leaves",
      "pairs_with": "cloves",
      "strength": 1
    },
    {
      "name": "allspice berries",
      "pairs_with": "cloves",
      "strength": 1
    },
    {
      "name": "scotch bonnet peppers",
      "pairs_with": "cloves",
      "strength": 1
    },
    {
      "name": "serrano chili",
      "pairs_with": "cloves",
      "strength": 1
    },
    {
      "name": "chorizo",
      "pairs_with": "cloves",
      "strength": 1
    },
    {
      "name": "bunch cilantro",
      "pairs_with": "cloves",
      "strength": 1
    },
    {
      "name": "roasted tomatoes",
      "pairs_with": "cloves",
      "strength": 1
    },
    {
      "name": "pinch saffron",
      "pairs_with": "cloves",
      "strength": 1
    }
  ],
  "novel_from_b": [
    {
      "name": "heads garlic",
      "pairs_with": "olive oil",
      "strength": 1
    },
    {
      "name": "palm",
      "pairs_with": "olive oil",
      "strength": 1
    },
    {
      "name": "pasta",
      "pairs_with": "olive oil",
      "strength": 1
    },
    {
      "name": "cremini",
      "pairs_with": "olive oil",
      "strength": 1
    },
    {
      "name": "squid",
      "pairs_with": "olive oil",
      "strength": 1
    },
    {
      "name": "baby arugula",
      "pairs_with": "olive oil",
      "strength": 1
    },
    {
      "name": "turkey sausage",
      "pairs_with": "olive oil",
      "strength": 1
    },
    {
      "name": "spaghetti",
      "pairs_with": "olive oil",
      "strength": 1
    },
    {
      "name": "spun",
      "pairs_with": "olive oil",
      "strength": 1
    },
    {
      "name": "anchovies",
      "pairs_with": "olive oil",
      "strength": 1
    }
  ]
}