{
  "pair": "Greek + Italian",
  "bridges": [
    {
      "name": "feta cheese",
      "score": 90.01905667086434,
      "connects_a": [
        "cherry tomatoes",
        "olives",
        "dill"
      ],
      "connects_b": [
        "seasoning",
        "tomatoes",
        "parsley"
      ]
    },
    {
      "name": "can tomatoes",
      "score": 84.49441628721962,
      "connects_a": [
        "bell pepper",
        "olives",
        "parsley"
      ],
      "connects_b": [
        "freshly",
        "bell pepper",
        "mozzarella cheese"
      ]
    },
    {
      "name": "capers",
      "score": 80.15597431040385,
      "connects_a": [
        "cherry tomatoes",
        "olives",
        "wine vinegar"
      ],
      "connects_b": [
        "pepper flakes",
        "tomatoes",
        "parsley"
      ]
    },
    {
      "name": "oregano",
      "score": 72.40333124383577,
      "connects_a": [
        "bell pepper",
        "olives",
        "cheese crumbles"
      ],
      "connects_b": [
        "bell pepper",
        "mozzarella cheese",
        "tomatoes"
      ]
    },
    {
      "name": "basil",
      "score": 63.08115787444858,
      "connects_a": [
        "olives",
        "spinach",
        "tomatoes"
      ],
      "connects_b": [
        "parmesan cheese",
        "seasoning",
        "mozzarella cheese"
      ]
    },
    {
      "name": "tomato paste",
      "score": 60.387166593818115,
      "connects_a": [
        "bell pepper",
        "tomatoes",
        "parsley"
      ],
      "connects_b": [
        "bell pepper",
        "tomatoes",
        "carrot"
      ]
    },
    {
      "name": "cans tomatoes",
      "score": 60.133284954817384,
      "connects_a": [
        "grain sea salt",
        "onion",
        "oregano"
      ],
      "connects_b": [
        "pepper flakes",
        "seasoning",
        "optional"
      ]
    },
    {
      "name": "kalamata olives",
      "score": 60.08175132994992,
      "connects_a": [
        "cherry tomatoes",
        "olives",
        "olive oil"
      ],
      "connects_b": [
        "olive oil",
        "tomatoes",
        "oregano"
      ]
    },
    {
      "name": "veal",
      "score": 55.14990137839551,
      "connects_a": [
        "milk",
        "parsley",
        "oregano"
      ],
      "connects_b": [
        "parmesan cheese",
        "freshly",
        "milk"
      ]
    },
    {
      "name": "spaghetti",
      "score": 55.10785457716198,
      "connects_a": [
        "parsley",
        "oregano",
        "cloves"
      ],
      "connects_b": [
        "parmesan cheese",
        "freshly",
        "pepper flakes"
      ]
    }
  ],
  "novel_from_a": [
    {
      "name": "chipotles",
      "pairs_with": "cloves",
      "strength": 1
    },
    {
      "name": "muscovado sugar",
      "pairs_with": "butter",
      "strength": 1
    },
    {
      "name": "garam masala",
      "pairs_with": "onion",
      "strength": 1
    },
    {
      "name": "pinto",
      "pairs_with": "onion",
      "strength": 1
    },
    {
      "name": "jicama",
      "pairs_with": "carrot",
      "strength": 1
    },
    {
      "name": "water chestnuts",
      "pairs_with": "carrot",
      "strength": 1
    },
    {
      "name": "pepper jack cheese",
      "pairs_with": "bell pepper",
      "strength": 1
    },
    {
      "name": "pepper jack cheese",
      "pairs_with": "cream",
      "strength": 1
    },
    {
      "name": "tahini",
      "pairs_with": "parsley",
      "strength": 1
    },
    {
      "name": "corn starch",
      "pairs_with": "garlic",
      "strength": 1
    }
  ],
  "novel_from_b": [
    {
      "name": "bucatini",
      "pairs_with": "olive oil",
      "strength": 1
    },
    {
      "name": "grigio",
      "pairs_with": "olive oil",
      "strength": 1
    },
    {
      "name": "radicchio",
      "pairs_with": "olive oil",
      "strength": 1
    },
    {
      "name": "sandwich rolls",
      "pairs_with": "olive oil",
      "strength": 1
    },
    {
      "name": "mussels",
      "pairs_with": "olive oil",
      "strength": 1
    },
    {
      "name": "fettuccine",
      "pairs_with": "olive oil",
      "strength": 1
    },
    {
      "name": "micro greens",
      "pairs_with": "olive oil",
      "strength": 1
    },
    {
      "name": "basil chiffonade",
      "pairs_with": "olive oil",
      "strength": 1
    },
    {
      "name": "cannellini beans",
      "pairs_with": "olive oil",
      "strength": 1
    },
    {
      "name": "chorizo sausage",
      "pairs_with": "olive oil",
      "strength": 1
    }
  ]
}