{
  "pair": "African + American",
  "bridges": [
    {
      "name": "garam masala",
      "score": 112.63312577889056,
      "connects_a": [
        "tomato paste",
        "ginger",
        "cumin"
      ],
      "connects_b": [
        "cumin",
        "vegetable oil",
        "garlic"
      ]
    },
    {
      "name": "palm",
      "score": 77.29629018752723,
      "connects_a": [
        "cumin",
        "chicken stock",
        "scallions"
      ],
      "connects_b": [
        "cumin",
        "cloves",
        "parsley"
      ]
    },
    {
      "name": "chiles",
      "score": 70.33408636028797,
      "connects_a": [
        "cilantro leaves",
        "ginger",
        "cumin"
      ],
      "connects_b": [
        "cumin",
        "cloves",
        "vegetable oil"
      ]
    },
    {
      "name": "ribs celery",
      "score": 63.459137120032835,
      "connects_a": [
        "tomato paste",
        "chicken stock",
        "scallions"
      ],
      "connects_b": [
        "cloves",
        "parsley",
        "optional"
      ]
    },
    {
      "name": "tomato paste",
      "score": 63.406524923509025,
      "connects_a": [
        "cumin",
        "turmeric",
        "cloves"
      ],
      "connects_b": [
        "cumin",
        "cloves",
        "parsley"
      ]
    },
    {
      "name": "cardamom pods",
      "score": 60.12332152757244,
      "connects_a": [
        "ginger",
        "cumin",
        "turmeric"
      ],
      "connects_b": [
        "cumin",
        "cloves",
        "vegetable oil"
      ]
    },
    {
      "name": "bay leaf",
      "score": 50.44997739963467,
      "connects_a": [
        "tomato paste",
        "cumin",
        "chicken stock"
      ],
      "connects_b": [
        "cumin",
        "parsley",
        "tomatoes"
      ]
    },
    {
      "name": "grits",
      "score": 49.191700254640224,
      "connects_a": [
        "chicken stock",
        "scallions",
        "butter"
      ],
      "connects_b": [
        "butter",
        "parsley",
        "cream"
      ]
    },
    {
      "name": "can tomatoes",
      "score": 48.282523592696926,
      "connects_a": [
        "tomato paste",
        "cumin",
        "cloves"
      ],
      "connects_b": [
        "cumin",
        "cloves",
        "parsley"
      ]
    },
    {
      "name": "celery",
      "score": 48.11914764879769,
      "connects_a": [
        "tomato paste",
        "chicken stock",
        "parsley"
      ],
      "connects_b": [
        "parsley",
        "garlic",
        "tomatoes"
      ]
    }
  ],
  "novel_from_a": [
    {
      "name": "lamb shoulder",
      "pairs_with": "onion",
      "strength": 1
    },
    {
      "name": "powder mint",
      "pairs_with": "leaves",
      "strength": 1
    },
    {
      "name": "cloves cardamom",
      "pairs_with": "leaves",
      "strength": 1
    }
  ],
  "novel_from_b": [
    {
      "name": "radicchio",
      "pairs_with": "olive oil",
      "strength": 1
    },
    {
      "name": "sherry vinegar",
      "pairs_with": "olive oil",
      "strength": 1
    },
    {
      "name": "crusty bread",
      "pairs_with": "olive oil",
      "strength": 1
    },
    {
      "name": "heads garlic",
      "pairs_with": "olive oil",
      "strength": 1
    },
    {
      "name": "romano",
      "pairs_with": "olive oil",
      "strength": 1
    },
    {
      "name": "arugula",
      "pairs_with": "olive oil",
      "strength": 1
    },
    {
      "name": "penne pasta",
      "pairs_with": "olive oil",
      "strength": 1
    },
    {
      "name": "pass",
      "pairs_with": "olive oil",
      "strength": 1
    },
    {
      "name": "mortadella",
      "pairs_with": "olive oil",
      "strength": 1
    },
    {
      "name": "cannellini",
      "pairs_with": "olive oil",
      "strength": 1
    }
  ]
}