{
  "pair": "Irish + Pakistan",
  "bridges": [
    {
      "name": "garam masala",
      "score": 108.61051414393017,
      "connects_a": [
        "onion",
        "potatoes",
        "garlic"
      ],
      "connects_b": [
        "cinnamon sticks",
        "tomatoes",
        "cardamom"
      ]
    },
    {
      "name": "tomato paste",
      "score": 56.36135548756358,
      "connects_a": [
        "parsley",
        "russet potatoes",
        "cloves"
      ],
      "connects_b": [
        "garam masala",
        "turmeric",
        "cloves"
      ]
    },
    {
      "name": "allspice",
      "score": 55.24504729138824,
      "connects_a": [
        "raisins",
        "kosher sea salt",
        "thyme"
      ],
      "connects_b": [
        "mustard seeds",
        "cinnamon sticks",
        "cayenne pepper"
      ]
    },
    {
      "name": "bay leaf",
      "score": 54.485975591605445,
      "connects_a": [
        "parsley",
        "russet potatoes",
        "carrot"
      ],
      "connects_b": [
        "garam masala",
        "turmeric",
        "cinnamon sticks"
      ]
    },
    {
      "name": "tumeric",
      "score": 54.15285920668306,
      "connects_a": [
        "onion",
        "potatoes",
        "garlic"
      ],
      "connects_b": [
        "garam masala",
        "mustard seeds",
        "cayenne pepper"
      ]
    },
    {
      "name": "coriander powder",
      "score": 48.093729141204676,
      "connects_a": [
        "onion",
        "leaves",
        "garlic"
      ],
      "connects_b": [
        "garam masala",
        "turmeric",
        "tomatoes"
      ]
    },
    {
      "name": "cardamom pods",
      "score": 42.086325069300706,
      "connects_a": [
        "cloves",
        "raisins",
        "vegetable oil"
      ],
      "connects_b": [
        "garam masala",
        "turmeric",
        "cinnamon sticks"
      ]
    },
    {
      "name": "cumin seeds",
      "score": 42.051821498233515,
      "connects_a": [
        "potatoes",
        "raisins"
      ],
      "connects_b": [
        "cinnamon sticks",
        "tomatoes",
        "cardamom"
      ]
    },
    {
      "name": "chiles",
      "score": 39.186133829303294,
      "connects_a": [
        "cloves",
        "vegetable oil",
        "2"
      ],
      "connects_b": [
        "garam masala",
        "turmeric",
        "mustard seeds"
      ]
    },
    {
      "name": "curry powder",
      "score": 39.018667252206576,
      "connects_a": [
        "carrot",
        "potatoes",
        "raisins"
      ],
      "connects_b": [
        "garam masala",
        "turmeric",
        "mustard seeds"
      ]
    }
  ],
  "novel_from_a": [
    {
      "name": "capers",
      "pairs_with": "olive oil",
      "strength": 1
    },
    {
      "name": "head fennel",
      "pairs_with": "olive oil",
      "strength": 1
    },
    {
      "name": "olives",
      "pairs_with": "olive oil",
      "strength": 1
    },
    {
      "name": "sherry vinegar",
      "pairs_with": "olive oil",
      "strength": 1
    },
    {
      "name": "bunch kale",
      "pairs_with": "olive oil",
      "strength": 1
    },
    {
      "name": "palm",
      "pairs_with": "olive oil",
      "strength": 1
    },
    {
      "name": "beef chuck",
      "pairs_with": "cloves",
      "strength": 1
    },
    {
      "name": "allspice berries",
      "pairs_with": "cloves",
      "strength": 1
    },
    {
      "name": "inch piece",
      "pairs_with": "cloves",
      "strength": 1
    },
    {
      "name": "chipotles",
      "pairs_with": "cloves",
      "strength": 1
    }
  ],
  "novel_from_b": [
    {
      "name": "petite",
      "pairs_with": "olive oil",
      "strength": 1
    },
    {
      "name": "couscous",
      "pairs_with": "olive oil",
      "strength": 1
    },
    {
      "name": "lamb shanks",
      "pairs_with": "olive oil",
      "strength": 1
    },
    {
      "name": "chiles",
      "pairs_with": "cloves",
      "strength": 1
    },
    {
      "name": "petite",
      "pairs_with": "cloves",
      "strength": 1
    },
    {
      "name": "serrano",
      "pairs_with": "cloves",
      "strength": 1
    },
    {
      "name": "saffron threads",
      "pairs_with": "cloves",
      "strength": 1
    },
    {
      "name": "cardamom pods",
      "pairs_with": "cloves",
      "strength": 1
    },
    {
      "name": "chile",
      "pairs_with": "cloves",
      "strength": 1
    },
    {
      "name": "lamb shanks",
      "pairs_with": "cloves",
      "strength": 1
    }
  ]
}