{
  "pair": "Chinese + French",
  "bridges": [
    {
      "name": "bean sprouts",
      "score": 68.14430273859602,
      "connects_a": [
        "peanut oil",
        "sesame oil",
        "carrot"
      ],
      "connects_b": [
        "wine vinegar",
        "shallots",
        "carrot"
      ]
    },
    {
      "name": "ribs celery",
      "score": 56.40812188447363,
      "connects_a": [
        "carrot",
        "scallions",
        "onion"
      ],
      "connects_b": [
        "carrot",
        "wine",
        "onion"
      ]
    },
    {
      "name": "fish sauce",
      "score": 54.53091368938329,
      "connects_a": [
        "peanut oil",
        "noodles",
        "carrot"
      ],
      "connects_b": [
        "shallots",
        "carrot",
        "vegetable oil"
      ]
    },
    {
      "name": "inch piece",
      "score": 52.15555698632034,
      "connects_a": [
        "peanut oil",
        "sesame oil",
        "carrot"
      ],
      "connects_b": [
        "wine vinegar",
        "cloves",
        "carrot"
      ]
    },
    {
      "name": "shiitake",
      "score": 51.037808096377105,
      "connects_a": [
        "peanut oil",
        "sesame oil",
        "carrot"
      ],
      "connects_b": [
        "shallots",
        "carrot",
        "thyme"
      ]
    },
    {
      "name": "hoisin sauce",
      "score": 44.033640231655724,
      "connects_a": [
        "carrot",
        "spice powder",
        "ginger"
      ],
      "connects_b": [
        "garlic",
        "carrot"
      ]
    },
    {
      "name": "oyster sauce",
      "score": 44.02828845373891,
      "connects_a": [
        "spice powder",
        "oil",
        "ginger"
      ],
      "connects_b": [
        "garlic",
        "vegetable oil"
      ]
    },
    {
      "name": "celery",
      "score": 42.10425419269799,
      "connects_a": [
        "carrot",
        "onion",
        "garlic"
      ],
      "connects_b": [
        "carrot",
        "bay leaf",
        "onion"
      ]
    },
    {
      "name": "corn starch",
      "score": 40.07939969178618,
      "connects_a": [
        "oil",
        "ginger",
        "peanut oil"
      ],
      "connects_b": [
        "garlic",
        "egg whites"
      ]
    },
    {
      "name": "garam masala",
      "score": 36.203504714643394,
      "connects_a": [
        "oil",
        "onion",
        "vegetable oil"
      ],
      "connects_b": [
        "bay leaf",
        "onion",
        "vegetable oil"
      ]
    }
  ],
  "novel_from_a": [
    {
      "name": "squid",
      "pairs_with": "olive oil",
      "strength": 1
    },
    {
      "name": "stalk lemongrass",
      "pairs_with": "cloves",
      "strength": 1
    },
    {
      "name": "white onion",
      "pairs_with": "cloves",
      "strength": 1
    },
    {
      "name": "black beans",
      "pairs_with": "cloves",
      "strength": 1
    },
    {
      "name": "fresno",
      "pairs_with": "cloves",
      "strength": 1
    },
    {
      "name": "wheat spaghetti",
      "pairs_with": "cloves",
      "strength": 1
    },
    {
      "name": "sodium",
      "pairs_with": "cloves",
      "strength": 1
    },
    {
      "name": "tomatillos",
      "pairs_with": "cloves",
      "strength": 1
    },
    {
      "name": "squid",
      "pairs_with": "cloves",
      "strength": 1
    },
    {
      "name": "piece ginger",
      "pairs_with": "cloves",
      "strength": 1
    }
  ],
  "novel_from_b": [
    {
      "name": "or finely",
      "pairs_with": "cloves",
      "strength": 1
    },
    {
      "name": "slab bacon",
      "pairs_with": "cloves",
      "strength": 1
    },
    {
      "name": "chorizo",
      "pairs_with": "cloves",
      "strength": 1
    },
    {
      "name": "marzano",
      "pairs_with": "cloves",
      "strength": 1
    },
    {
      "name": "have",
      "pairs_with": "cloves",
      "strength": 1
    },
    {
      "name": "jalapeno chile",
      "pairs_with": "cloves",
      "strength": 1
    },
    {
      "name": "romano",
      "pairs_with": "cloves",
      "strength": 1
    },
    {
      "name": "leg",
      "pairs_with": "cloves",
      "strength": 1
    },
    {
      "name": "cardamom pods",
      "pairs_with": "cloves",
      "strength": 1
    },
    {
      "name": "bundle",
      "pairs_with": "cloves",
      "strength": 1
    }
  ]
}